ratex/__init__.py
ratex/adjust.py
ratex/build.py
ratex/errors.py
ratex/flex.py
ratex/header.py
ratex/list.py
ratex/packages.py
ratex/space.py
ratex/table.py
ratex/text.py
ratex-0.2.9.613.dist-info/LICENSE
ratex-0.2.9.613.dist-info/METADATA
ratex-0.2.9.613.dist-info/WHEEL
ratex-0.2.9.613.dist-info/top_level.txt
ratex-0.2.9.613.dist-info/RECORD
