Metadata-Version: 2.1
Name: ratex
Version: 0.2.9.613
Summary: Efficiently Build LaTeX PDF Documents with Python
Home-page: https://github.com/realTristan/ratex
Author: Tristan Simpson
Author-email: heytristaann@gmail.com
Project-URL: Bug Tracker, https://github.com/realTristan/ratex/issues
Classifier: Programming Language :: Python :: 3
Classifier: License :: OSI Approved :: MIT License
Classifier: Operating System :: OS Independent
Requires-Python: >=3.6
License-File: LICENSE
